takopi_pinnacle/__init__.py
takopi_pinnacle/backend.py
takopi_pinnacle/bundle.py
takopi_pinnacle/gitutils.py
takopi_pinnacle/repomap.py
takopi_pinnacle/ship.py
takopi_pinnacle/prompts/plan_system.md
takopi_pinnacle/prompts/review_system.md
takopi_pinnacle-0.1.2.dist-info/METADATA
takopi_pinnacle-0.1.2.dist-info/WHEEL
takopi_pinnacle-0.1.2.dist-info/entry_points.txt
takopi_pinnacle-0.1.2.dist-info/licenses/LICENSE
takopi_pinnacle-0.1.2.dist-info/RECORD
