Metadata-Version: 2.4
Name: takopi-pinnacle
Version: 0.1.2
Summary: Takopi command plugin to generate clean handoff bundles (plan + PR review) for LLM-assisted dev workflows.
Project-URL: Homepage, https://takopi.dev
Project-URL: Repository, https://example.com/your-org/takopi-pinnacle
Author: Pinnacle
License: MIT
License-File: LICENSE
Keywords: codex,llm,plugin,review,takopi,workflow
Requires-Python: >=3.14
Requires-Dist: takopi>=0.18
